sugar/__init__.py
sugar/__pkg__.py
sugar/arrays.py
sugar.py-0.1.1.dist-info/DESCRIPTION.rst
sugar.py-0.1.1.dist-info/METADATA
sugar.py-0.1.1.dist-info/RECORD
sugar.py-0.1.1.dist-info/WHEEL
sugar.py-0.1.1.dist-info/metadata.json
sugar.py-0.1.1.dist-info/top_level.txt
