Metadata-Version: 2.0
Name: sugar.py
Version: 0.1.1
Summary: Python utility library. Based on sugar Javascript Library.
Home-page: https://github.com/bharadwajyarlagadda/sugar.py
Author: Bharadwaj Yarlagadda
Author-email: yarlagaddabharadwaj@gmail.com
License: MIT License
Keywords: sugarjs sugar utility utilities js javascript
Platform: UNKNOWN
Classifier: Development Status :: 2 - Pre-Alpha
Classifier: Intended Audience :: Developers
Classifier: Operating System :: OS Independent
Classifier: Programming Language :: Python
Classifier: License :: OSI Approved :: MIT License
Classifier: Topic :: Software Development :: Libraries
Classifier: Topic :: Software Development :: Libraries :: Python Modules
Classifier: Programming Language :: Python
Classifier: Programming Language :: Python :: 2
Classifier: Programming Language :: Python :: 2.7
Classifier: Programming Language :: Python :: 3
Classifier: Programming Language :: Python :: 3.3
Classifier: Programming Language :: Python :: 3.4
Classifier: Programming Language :: Python :: 3.5
